mutview/__init__.py
mutview/process.py
mutview/utils.py
mutview-0.0.1.dist-info/LICENSE
mutview-0.0.1.dist-info/METADATA
mutview-0.0.1.dist-info/WHEEL
mutview-0.0.1.dist-info/entry_points.txt
mutview-0.0.1.dist-info/top_level.txt
mutview-0.0.1.dist-info/RECORD
