Metadata-Version: 2.1
Name: mutview
Version: 0.0.1
Summary: A command tool to view reads over a loci from bam file, like a lightweigth IGV
Author-email: Li Teng <707704459@qq.com>
Project-URL: Homepage, https://github.com/TuBieJun/MutView
Project-URL: Issues, https://github.com/TuBieJun/MutView/issues
Classifier: Programming Language :: Python :: 3
Classifier: License :: OSI Approved :: MIT License
Classifier: Operating System :: OS Independent
Requires-Python: >=3.7
License-File: LICENSE
Requires-Dist: pysam
